Metadata-Version: 2.1
Name: sumandmul
Version: 0.0.2
Summary: A package for summarizing array and multiplying the result on a number
Home-page: https://github.com/brenscrazy/sumandmulitlyer
Author: Vinnikov Gleb
Author-email: glebmanufa@gmail.com
License: UNKNOWN
Platform: UNKNOWN
